wandb_allennlp/__init__.py
wandb_allennlp/__main__.py
wandb_allennlp/config.py
wandb_allennlp/utils.py
wandb_allennlp/versioned.py
wandb_allennlp/commands/__init__.py
wandb_allennlp/commands/download_from_wandb.py
wandb_allennlp/commands/parser_base.py
wandb_allennlp/commands/train_with_wandb.py
wandb_allennlp/training/__init__.py
wandb_allennlp/training/train_and_test.py
wandb_allennlp/training/callbacks/__init__.py
wandb_allennlp/training/callbacks/log_to_wandb.py
wandb_allennlp/training/callbacks/subcallbacks.py
wandb_allennlp/training/callbacks/utils.py
wandb_allennlp-0.3.3.dist-info/LICENSE
wandb_allennlp-0.3.3.dist-info/METADATA
wandb_allennlp-0.3.3.dist-info/WHEEL
wandb_allennlp-0.3.3.dist-info/top_level.txt
wandb_allennlp-0.3.3.dist-info/RECORD
