Metadata-Version: 2.1
Name: wandb-allennlp
Version: 0.3.3
Summary: Utilities to use allennlp with wandb
Home-page: https://github.com/dhruvdcoder/wandb-allennlp
Author: Dhruvesh Patel
Author-email: 1793dnp@gmail.com
Classifier: Programming Language :: Python :: 3
Classifier: License :: OSI Approved :: MIT License
Classifier: Operating System :: OS Independent
Requires-Python: >=3.6
License-File: LICENSE
Requires-Dist: allennlp (>=2.5.0)
Requires-Dist: wandb (>=0.10.11)
Requires-Dist: pyyaml
Requires-Dist: tensorboard
Requires-Dist: overrides
Requires-Dist: shortuuid
